{
  "db_name": "SQLite",
  "query": "WITH TmpDelta(delta, created_at, cfg_hash) AS (\n    SELECT\n        delta,\n        created_at,\n        cfg_hash\n    FROM\n        Deltas\n    WHERE\n        cfg_hash = (\n            WITH HashVer(cfg_hash, version) AS (\n                SELECT\n                    cfg_hash,\n                    version\n                FROM\n                    BaseCfgs\n                WHERE\n                    name = $1\n            )\n            SELECT\n                cfg_hash\n            FROM\n                HashVer\n            WHERE\n                version = (\n                    SELECT\n                        MAX(version)\n                    FROM\n                        HashVer\n                )\n            LIMIT\n                1\n        )\n)\nSELECT\n    delta AS \"delta: Value\", cfg_hash\nFROM\n    TmpDelta\nWHERE\n    created_at = (\n        SELECT\n            MAX(created_at)\n        FROM\n            TmpDelta\n    );\n",
  "describe": {
    "columns": [
      {
        "name": "delta: Value",
        "ordinal": 0,
        "type_info": "Null"
      },
      {
        "name": "cfg_hash",
        "ordinal": 1,
        "type_info": "Text"
      }
    ],
    "parameters": {
      "Right": 1
    },
    "nullable": [
      false,
      false
    ]
  },
  "hash": "9ea1b84e4203100278f2da31aa2d3eb86083556f5c0e80f4cc5173645733d1c6"
}
